{
	"configurations" : 
	[
		{
			"directories" : 
			[
				{
					"build" : ".",
					"minimumCMakeVersion" : 
					{
						"string" : "3.4.1"
					},
					"projectIndex" : 0,
					"source" : ".",
					"targetIndexes" : 
					[
						0
					]
				}
			],
			"name" : "Debug",
			"projects" : 
			[
				{
					"directoryIndexes" : 
					[
						0
					],
					"name" : "retinafacencnn",
					"targetIndexes" : 
					[
						0
					]
				}
			],
			"targets" : 
			[
				{
					"directoryIndex" : 0,
					"id" : "retinafacencnn::@6890427a1f51a3e7e1df",
					"jsonFile" : "target-retinafacencnn-Debug-ae55d29a6940c8a818da.json",
					"name" : "retinafacencnn",
					"projectIndex" : 0
				}
			]
		}
	],
	"kind" : "codemodel",
	"paths" : 
	{
		"build" : "C:/Users/maozii/Desktop/nihuiscrfd/demo1/app/.cxx/Debug/406i3ji2/armeabi-v7a",
		"source" : "C:/Users/maozii/Desktop/nihuiscrfd/demo1/app/src/main/cpp"
	},
	"version" : 
	{
		"major" : 2,
		"minor" : 1
	}
}
